skyscanner_b2b/__init__.py
skyscanner_b2b/sdk.py
skyscanner_b2b/hooks/__init__.py
skyscanner_b2b/hooks/hook.py
skyscanner_b2b/models/__init__.py
skyscanner_b2b/models/autosuggest_carhire_request.py
skyscanner_b2b/models/autosuggest_flights_request.py
skyscanner_b2b/models/autosuggest_hotels_request.py
skyscanner_b2b/models/base.py
skyscanner_b2b/models/hierarchy_flights_nearest_request.py
skyscanner_b2b/models/itineraryrefresh_create_request.py
skyscanner_b2b/models/utils/cast_models.py
skyscanner_b2b/models/utils/json_map.py
skyscanner_b2b/net/__init__.py
skyscanner_b2b/net/environment/__init__.py
skyscanner_b2b/net/environment/environment.py
skyscanner_b2b/net/headers/__init__.py
skyscanner_b2b/net/headers/api_key_auth.py
skyscanner_b2b/net/headers/base_header.py
skyscanner_b2b/net/request_chain/__init__.py
skyscanner_b2b/net/request_chain/request_chain.py
skyscanner_b2b/net/request_chain/handlers/__init__.py
skyscanner_b2b/net/request_chain/handlers/base_handler.py
skyscanner_b2b/net/request_chain/handlers/hook_handler.py
skyscanner_b2b/net/request_chain/handlers/http_handler.py
skyscanner_b2b/net/request_chain/handlers/retry_handler.py
skyscanner_b2b/net/transport/__init__.py
skyscanner_b2b/net/transport/request.py
skyscanner_b2b/net/transport/request_error.py
skyscanner_b2b/net/transport/response.py
skyscanner_b2b/net/transport/serializer.py
skyscanner_b2b/net/transport/utils.py
skyscanner_b2b/services/__init__.py
skyscanner_b2b/services/autosuggest.py
skyscanner_b2b/services/carriers.py
skyscanner_b2b/services/culture.py
skyscanner_b2b/services/flights_indicative_prices.py
skyscanner_b2b/services/flights_live_prices.py
skyscanner_b2b/services/geo.py
skyscanner_b2b/services/utils/base_service.py
skyscanner_b2b/services/utils/default_headers.py
skyscanner_b2b/services/utils/validator.py
skyscanner_b2b-1.0.0.dist-info/LICENSE
skyscanner_b2b-1.0.0.dist-info/METADATA
skyscanner_b2b-1.0.0.dist-info/WHEEL
skyscanner_b2b-1.0.0.dist-info/top_level.txt
skyscanner_b2b-1.0.0.dist-info/RECORD
