Metadata-Version: 2.1
Name: skyscanner-b2b
Version: 1.0.0
Summary: Our Travel APIs are provided to connect partners like yourself to all the data you need to build an innovative website or app using our Skyscanner travel content. We’ve made it easier than ever to develop your website using flexible price search options so you can build exciting tools that will expand your travel search options for your users.
License: MIT
Requires-Python: >=3.7
License-File: LICENSE
Requires-Dist: requests >=2.31.0
